MANIFEST.in
README.md
requirements.txt
setup.py
geneRNI/benchmarks.py
geneRNI/core.py
geneRNI/data.py
geneRNI/evaluation.py
geneRNI/links.py
geneRNI/search_param.py
geneRNI/types_.py
geneRNI/utils.py
geneRNI.egg-info/PKG-INFO
geneRNI.egg-info/SOURCES.txt
geneRNI.egg-info/dependency_links.txt
geneRNI.egg-info/requires.txt
geneRNI.egg-info/top_level.txt
geneRNI/grn/__init__.py
geneRNI/grn/correction.py
geneRNI/models/__init__.py
geneRNI/models/base.py
geneRNI/models/hgb.py
geneRNI/models/rf.py
geneRNI/models/ridge.py
geneRNI/models/sgd.py
tests/test-cv.py
tests/test-data.py
tests/test-feature-importances.py
tests/test-grid-search.py
tests/test-utils.py