Metadata-Version: 2.1
Name: geneRNI
Version: 1.0.2
Summary: A Python package for gene regulatory network inference
Home-page: https://github.com/janursa/geneRNI
Author: Jalil Nourisa, Antoine Passemiers
Author-email: jalil.nourisa@gmail.com
Classifier: Programming Language :: Python :: 3
Classifier: License :: OSI Approved :: MIT License
Classifier: Operating System :: OS Independent
Requires-Python: >=3.8
